{
  "version": "0.2.379",
  "description": "Bass tab analysis and practice workstation",
  "homepage": "https://basstab.pro",
  "license": "Proprietary",
  "url": "https://dev.basstab.pro/desktop/dev/windows-x64/bb63953/Basstab-Pro-windows-x64.zip",
  "hash": "d1338076eaaec3ecb2293128fdb5267e02ad9fce2ed78264e005556814dc2f11",
  "shortcuts": [
    ["Basstab Pro.exe", "Basstab Pro"]
  ],
  "checkver": {
    "url": "https://dev.basstab.pro/desktop/dev/latest.json",
    "jsonpath": "$.version"
  },
  "autoupdate": {
    "url": "https://dev.basstab.pro/desktop/dev/windows-x64/latest/Basstab-Pro-windows-x64.zip"
  }
}
