{
  "version": "0.2.356",
  "description": "Bass tab analysis and practice workstation",
  "homepage": "https://basstab.pro",
  "license": "Proprietary",
  "url": "https://dev.basstab.pro/desktop/dev/windows-x64/58da5d8/Basstab-Pro-windows-x64.zip",
  "hash": "d8d8141a1cc7145b4eaf73997e245421c1df58bfa054327775d2b08c082d2cd0",
  "shortcuts": [
    ["Basstab Pro.exe", "Basstab Pro"]
  ],
  "checkver": {
    "url": "https://dev.basstab.pro/desktop/dev/latest.json",
    "jsonpath": "$.version"
  },
  "autoupdate": {
    "url": "https://dev.basstab.pro/desktop/dev/windows-x64/latest/Basstab-Pro-windows-x64.zip"
  }
}
